smsframework_africastalking/__init__.py
smsframework_africastalking/error.py
smsframework_africastalking/provider.py
smsframework_africastalking-1.0.3.dist-info/LICENSE
smsframework_africastalking-1.0.3.dist-info/METADATA
smsframework_africastalking-1.0.3.dist-info/WHEEL
smsframework_africastalking-1.0.3.dist-info/top_level.txt
smsframework_africastalking-1.0.3.dist-info/RECORD
