Metadata-Version: 2.1
Name: smsframework-africastalking
Version: 1.0.3
Summary: SMS framework: Africa's Talking provider
Home-page: https://github.com/BBOXX/py-smsframework-africastalking
Author: BBOXX
Author-email: j.lynch@bboxx.co.uk
License: UNKNOWN
Keywords: sms message send africa africastalking smsframework provider
Platform: UNKNOWN
Classifier: Development Status :: 3 - Alpha
Classifier: Intended Audience :: Developers
Classifier: License :: OSI Approved :: MIT License
Classifier: Natural Language :: English
Classifier: Operating System :: OS Independent
Classifier: Programming Language :: Python :: 3
